{
    "18218033": {
        "title": "Kamu pernah menang Typeracer <span class='text-yellow'>dua kali</span>!",
        "subtitle": "Di tanggal 17 Mei 2020 kamu menang melawan Fabian, Evan, dan Pandyaka. Di tanggal 12 Juli 2020, kamu menang melawan Pandyaka (lagi) dan Zaldi. Keren!"
    },
    "13518022": {
        "title": "Kamu pernah jadi <span class='text-yellow'>Juara 2</span> lomba Typeracer!",
        "subtitle": "Di tanggal 17 Mei 2020 kamu mendapat juara dua, mengalahkan Evan dan Pandyaka.<br /><br />Makasih ya udah ngeramein #MaininKamu!"
    },
    "13518149": {
        "title": "Kamu pernah jadi finalis lomba Typeracer!",
        "subtitle": "Di tanggal 17 Mei 2020 kamu menjadi finalis Typeracer.<br /><br />Makasih ya udah ngeramein #MaininKamu!"
    },
    "13517003": {
        "title": "Kamu pernah jadi finalis lomba Typeracer <span class='text-yellow'>dua kali</span>!",
        "subtitle": "Di tanggal 17 Mei 2020 dan 12 Juli 2020 kamu menjadi finalis Typeracer. Kalah sama Scott dua kali tapi :(<br /><br />Makasih ya udah ngeramein #MaininKamu!"
    },
    "13518139": {
        "title": "Kamu pernah jadi <span class='text-yellow'>Juara 1</span> lomba Gartic!",
        "subtitle": "Di tanggal 31 Mei 2020 kamu menjadi pemenang Gartic.<br /><br />Makasih ya udah ngeramein #MaininKamu!"
    },
    "13516009": {
        "title": "Kamu pernah jadi <span class='text-yellow'>Juara 1</span> lomba Typeracer!",
        "subtitle": "Di tanggal 13 Juni 2020 kamu menang melawan Juro.<br /><br />Makasih ya udah ngeramein #MaininKamu!"
    },
    "13517113": {
        "title": "Kamu pernah jadi finalis lomba Typeracer!",
        "subtitle": "Di tanggal 13 Juni 2020 kamu menjadi finalis Typeracer.<br /><br />Makasih ya udah ngeramein #MaininKamu!"
    },
    "18218021": {
        "title": "Kamu pernah jadi <span class='text-yellow'>Juara 1</span> lomba Gartic tema ITB!",
        "subtitle": "Di tanggal 27 Juni 2020 kamu menjadi pemenang Gartic tema ITB.<br /><br />Makasih ya udah ngeramein #MaininKamu!"
    },
    "13517098": {
        "title": "Kamu pernah jadi finalis lomba Typeracer!",
        "subtitle": "Di tanggal 12 Juli 2020 kamu menjadi finalis Typeracer.<br /><br />Makasih ya udah ngeramein #MaininKamu!"
    },
    "18217018": {
        "title": "Kamu pernah jadi <span class='text-yellow'>Juara 1</span> lomba Gartic edisi Hari Kemerdekaan!",
        "subtitle": "Di tanggal 23 Agustus 2020 kamu menjadi pemenang Gartic edisi Hari Kemerdekaan.<br /><br />Makasih ya udah ngeramein #MaininKamu!"
    },
    "13518061": {
        "title": "Kamu pernah jadi <span class='text-yellow'>Juara 1</span> turnamen Stopots!",
        "subtitle": "Di tanggal 16 Januari 2021 kamu menjadi pemenang di turnamen Stopots, sekaligus <b>peserta terheboh!</b><br /><br />Makasih ya udah ngeramein #MaininKamu!"
    },
    "13518039": {
        "title": "Kamu pernah jadi <span class='text-yellow'>Juara 2</span> turnamen Stopots!",
        "subtitle": "Di tanggal 16 Januari 2021 kamu menjadi juara 2 di turnamen Stopots.<br /><br />Makasih ya udah ngeramein #MaininKamu!"
    },
    "13519039": {
        "title": "Kamu pernah jadi <span class='text-yellow'>Juara 1</span> turnamen Stopots!",
        "subtitle": "Di tanggal 16 Januari 2021 kamu menjadi pemenang di turnamen Stopots.<br /><br />Makasih ya udah ngeramein #MaininKamu!"
    },
    "13519154": {
        "title": "Kamu pernah jadi <span class='text-yellow'>Juara 2</span> turnamen Stopots!",
        "subtitle": "Di tanggal 16 Januari 2021 kamu menjadi juara 2 di turnamen Stopots.<br /><br />Makasih ya udah ngeramein #MaininKamu!"
    }
}